{"matchDate":"2023-06-06","matchRemark":"","matchType":"表演赛","matchMemberBPMode":"全部定员","matchMode":"队长模式","matchTeamList":[[{"player":"孙","order":"固定"},{"player":"黄","order":"固定"},{"player":"鹅","order":"固定"},{"player":"喵","order":"固定"},{"player":"钱","order":"固定"}],[{"player":"刘","order":"固定"},{"player":"灿","order":"固定"},{"player":"兔","order":"固定"},{"player":"鸽","order":"固定"},{"player":"桃","order":"固定"}]],"gameList":[{"gameType":"正常对局","winTeamIndex":0,"bpFirstTeamIndex":0,"bpHeroQueue":[],"teamList":[{"location":null,"heroList":[{"player":"孙","hero":"克林克兹"},{"player":"黄","hero":"潮汐猎人"},{"player":"鹅","hero":"幻影刺客"},{"player":"喵","hero":"小小"},{"player":"钱","hero":"杰奇洛"}]},{"location":null,"heroList":[{"player":"刘","hero":"裂魂人"},{"player":"灿","hero":"马格纳斯"},{"player":"兔","hero":"蝙蝠骑士"},{"player":"鸽","hero":"末日使者"},{"player":"桃","hero":"巫妖"}]}]}],"scoreList":[1,0],"playOffScoreList":[0,0],"winTeamIndex":0}